qs_codec/__init__.py
qs_codec/decode.py
qs_codec/encode.py
qs_codec/py.typed
qs_codec/enums/__init__.py
qs_codec/enums/charset.py
qs_codec/enums/decode_kind.py
qs_codec/enums/duplicates.py
qs_codec/enums/format.py
qs_codec/enums/list_format.py
qs_codec/enums/sentinel.py
qs_codec/models/__init__.py
qs_codec/models/decode_options.py
qs_codec/models/encode_options.py
qs_codec/models/overflow_dict.py
qs_codec/models/undefined.py
qs_codec/models/weak_wrapper.py
qs_codec/utils/__init__.py
qs_codec/utils/decode_utils.py
qs_codec/utils/encode_utils.py
qs_codec/utils/utils.py
qs_codec-1.4.0.dist-info/METADATA
qs_codec-1.4.0.dist-info/WHEEL
qs_codec-1.4.0.dist-info/licenses/LICENSE
qs_codec-1.4.0.dist-info/RECORD
