Metadata-Version: 2.4
Name: qs-codec
Version: 1.4.0
Summary: A query string encoding and decoding library for Python. Ported from qs for JavaScript.
Project-URL: Homepage, https://techouse.github.io/qs_codec/
Project-URL: Documentation, https://techouse.github.io/qs_codec/
Project-URL: Repository, https://github.com/techouse/qs_codec.git
Project-URL: Issues, https://github.com/techouse/qs_codec/issues
Project-URL: Changelog, https://github.com/techouse/qs_codec/blob/master/CHANGELOG.md
Project-URL: Sponsor, https://github.com/sponsors/techouse
Project-URL: PayPal, https://paypal.me/ktusar
Author-email: Klemen Tusar <techouse@gmail.com>
License-Expression: BSD-3-Clause
License-File: LICENSE
Keywords: arrays,brackets,codec,form-urlencoded,nested,percent-encoding,qs,query,query-string,querystring,rfc3986,url,urldecode,urlencode
Classifier: Development Status :: 5 - Production/Stable
Classifier: Environment :: Web Environment
Classifier: Intended Audience :: Developers
Classifier: License :: OSI Approved :: BSD License
Classifier: Operating System :: OS Independent
Classifier: Programming Language :: Python
Classifier: Programming Language :: Python :: 3
Classifier: Programming Language :: Python :: 3 :: Only
Classifier: Programming Language :: Python :: 3.8
Classifier: Programming Language :: Python :: 3.9
Classifier: Programming Language :: Python :: 3.10
Classifier: Programming Language :: Python :: 3.11
Classifier: Programming Language :: Python :: 3.12
Classifier: Programming Language :: Python :: 3.13
Classifier: Programming Language :: Python :: 3.14
Classifier: Programming Language :: Python :: Implementation :: CPython
Classifier: Programming Language :: Python :: Implementation :: PyPy
Classifier: Topic :: Internet :: WWW/HTTP
Classifier: Topic :: Internet :: WWW/HTTP :: Dynamic Content :: CGI Tools/Libraries
Classifier: Topic :: Software Development :: Libraries
Classifier: Topic :: Software Development :: Libraries :: Python Modules
Classifier: Topic :: Text Processing :: General
Classifier: Topic :: Utilities
Classifier: Typing :: Typed
Requires-Python: >=3.8
Provides-Extra: dev
Requires-Dist: bandit; extra == 'dev'
Requires-Dist: black; extra == 'dev'
Requires-Dist: flake8; extra == 'dev'
Requires-Dist: flake8-colors; extra == 'dev'
Requires-Dist: flake8-docstrings; extra == 'dev'
Requires-Dist: flake8-import-order; extra == 'dev'
Requires-Dist: flake8-typing-imports; extra == 'dev'
Requires-Dist: isort; extra == 'dev'
Requires-Dist: mypy<1.11; (python_version < '3.9') and extra == 'dev'
Requires-Dist: mypy<1.19; (python_version >= '3.9' and platform_python_implementation == 'PyPy') and extra == 'dev'
Requires-Dist: mypy>=1.11; (python_version >= '3.9' and platform_python_implementation != 'PyPy') and extra == 'dev'
Requires-Dist: pep8-naming; extra == 'dev'
Requires-Dist: pylint; extra == 'dev'
Requires-Dist: pyright; extra == 'dev'
Requires-Dist: pytest-cov>=5.0.0; extra == 'dev'
Requires-Dist: pytest>=8.1.2; extra == 'dev'
Requires-Dist: toml>=0.10.2; extra == 'dev'
Requires-Dist: tox; extra == 'dev'
